{
  "_meta": {
    "table": "MapDynamic_5079",
    "header_table": "MapDynamic_5079HeaderTable",
    "format": "flat_rows",
    "schema_size": 4,
    "row_count": 3,
    "array_fields": [
      "DisableVolume",
      "EnableVolume"
    ],
    "unresolved_array_refs": 6
  },
  "default": {
    "ID": "null",
    "Condition": "true",
    "EnableVolume": {},
    "DisableVolume": {}
  },
  "row_keys": [
    1,
    2,
    3
  ],
  "rows": [
    {
      "ID": 1,
      "Condition": "ed.ConditionX.IsExplStepFinished(13010105,3,4)",
      "EnableVolume": {
        "$arrayRef": 81036
      },
      "DisableVolume": {
        "$arrayRef": 81037
      }
    },
    {
      "ID": 2,
      "Condition": "ed.ConditionX.IsExplStepFinished(13010105,3,5)",
      "EnableVolume": {
        "$arrayRef": 81037
      },
      "DisableVolume": {
        "$arrayRef": 81036
      }
    },
    {
      "ID": 3,
      "Condition": "ed.ConditionX.IsExplStepFinished(13010113,4,2)",
      "EnableVolume": {
        "$arrayRef": 81036
      },
      "DisableVolume": {
        "$arrayRef": 81037
      }
    }
  ]
}
