{
  "_meta": {
    "table": "MapObj",
    "source_table": "MapObj",
    "format": "mapping_table",
    "entry_count": 1
  },
  "data": {
    "MapObj_5106IndexTable": {
      "Loc": {
        "340040": {
          "1": 510600001
        },
        "260023": {
          "1": 510600021,
          "2": 510600051
        },
        "280024": {
          "1": 510600022,
          "2": 510600048,
          "3": 510600050
        },
        "270024": {
          "1": 510600023
        },
        "290032": {
          "1": 510600024
        },
        "210026": {
          "1": 510600025
        },
        "310036": {
          "1": 510600026
        },
        "350038": {
          "1": 510600028
        },
        "330038": {
          "1": 510600029
        },
        "330039": {
          "1": 510600030
        },
        "410043": {
          "1": 510600031
        },
        "320039": {
          "1": 510600037,
          "2": 510600027
        },
        "230026": {
          "1": 510600041
        },
        "240028": {
          "1": 510600042
        },
        "220024": {
          "1": 510600043
        },
        "240029": {
          "1": 510600044
        },
        "220023": {
          "1": 510600045
        },
        "280027": {
          "1": 510600046
        },
        "310028": {
          "1": 510600047,
          "2": 510600049
        },
        "210038": {
          "1": 510600003,
          "2": 510600074
        },
        "210032": {
          "1": 510600004
        },
        "220032": {
          "1": 510600005
        },
        "270036": {
          "1": 510600006
        },
        "350037": {
          "1": 510600061
        },
        "360041": {
          "1": 510600065
        },
        "340042": {
          "1": 510600066
        },
        "220036": {
          "1": 510600068
        },
        "310046": {
          "1": 510600064,
          "2": 510600076
        },
        "200043": {
          "1": 510600070
        },
        "210037": {
          "1": 510600071
        },
        "220028": {
          "1": 510600072
        },
        "250022": {
          "1": 510600008
        },
        "260021": {
          "1": 510600009
        },
        "380040": {
          "1": 510600075
        },
        "200033": {
          "1": 510600082,
          "2": 510600084
        },
        "270039": {
          "1": 510600083
        },
        "200030": {
          "1": 510600085
        },
        "350042": {
          "1": 510600086
        },
        "370037": {
          "1": 510600087
        },
        "230036": {
          "1": 510600088
        },
        "210033": {
          "1": 510600089
        },
        "330041": {
          "1": 510600077
        },
        "250029": {
          "1": 510600078
        }
      },
      "ZoneID": {
        "1": {
          "1": 510600001,
          "2": 510600021,
          "3": 510600022,
          "4": 510600023,
          "5": 510600024,
          "6": 510600025,
          "7": 510600026,
          "8": 510600028,
          "9": 510600029,
          "10": 510600030,
          "11": 510600031,
          "12": 510600037,
          "13": 510600041,
          "14": 510600042,
          "15": 510600043,
          "16": 510600044,
          "17": 510600045,
          "18": 510600046,
          "19": 510600047,
          "20": 510600048,
          "21": 510600049,
          "22": 510600050,
          "23": 510600003,
          "24": 510600004,
          "25": 510600005,
          "26": 510600006,
          "27": 510600061,
          "28": 510600065,
          "29": 510600066,
          "30": 510600068,
          "31": 510600064,
          "32": 510600051,
          "33": 510600070,
          "34": 510600071,
          "35": 510600072,
          "36": 510600074,
          "37": 510600008,
          "38": 510600009,
          "39": 510600075,
          "40": 510600082,
          "41": 510600083,
          "42": 510600084,
          "43": 510600085,
          "44": 510600086,
          "45": 510600087,
          "46": 510600088,
          "47": 510600089,
          "48": 510600027,
          "49": 510600076,
          "50": 510600077,
          "51": 510600078
        }
      },
      "Type": {
        "24": {
          "1": 510600001,
          "2": 510600021,
          "3": 510600023,
          "4": 510600029,
          "5": 510600044,
          "6": 510600045,
          "7": 510600049,
          "8": 510600050,
          "9": 510600005,
          "10": 510600061,
          "11": 510600051,
          "12": 510600009
        },
        "23": {
          "1": 510600022,
          "2": 510600024,
          "3": 510600025,
          "4": 510600026,
          "5": 510600028,
          "6": 510600065,
          "7": 510600066,
          "8": 510600072,
          "9": 510600075,
          "10": 510600027,
          "11": 510600078
        },
        "26": {
          "1": 510600030,
          "2": 510600031,
          "3": 510600082,
          "4": 510600083,
          "5": 510600084,
          "6": 510600085,
          "7": 510600086,
          "8": 510600087
        },
        "39": {
          "1": 510600037,
          "2": 510600068,
          "3": 510600071,
          "4": 510600077
        },
        "11": {
          "1": 510600041,
          "2": 510600042,
          "3": 510600043,
          "4": 510600046,
          "5": 510600047,
          "6": 510600048
        },
        "8": {
          "1": 510600003,
          "2": 510600064,
          "3": 510600070,
          "4": 510600074,
          "5": 510600088,
          "6": 510600076
        },
        "38": {
          "1": 510600004,
          "2": 510600006
        },
        "6": {
          "1": 510600008
        },
        "59": {
          "1": 510600089
        }
      },
      "BattleGroupID": {
        "0": {
          "1": 510600001,
          "2": 510600021,
          "3": 510600022,
          "4": 510600023,
          "5": 510600024,
          "6": 510600025,
          "7": 510600026,
          "8": 510600028,
          "9": 510600029,
          "10": 510600030,
          "11": 510600031,
          "12": 510600037,
          "13": 510600041,
          "14": 510600042,
          "15": 510600043,
          "16": 510600044,
          "17": 510600045,
          "18": 510600046,
          "19": 510600047,
          "20": 510600048,
          "21": 510600049,
          "22": 510600050,
          "23": 510600003,
          "24": 510600004,
          "25": 510600005,
          "26": 510600006,
          "27": 510600061,
          "28": 510600065,
          "29": 510600066,
          "30": 510600068,
          "31": 510600064,
          "32": 510600051,
          "33": 510600070,
          "34": 510600071,
          "35": 510600072,
          "36": 510600074,
          "37": 510600008,
          "38": 510600009,
          "39": 510600075,
          "40": 510600082,
          "41": 510600083,
          "42": 510600084,
          "43": 510600085,
          "44": 510600086,
          "45": 510600087,
          "46": 510600088,
          "47": 510600089,
          "48": 510600027,
          "49": 510600076,
          "50": 510600077,
          "51": 510600078
        }
      },
      "ArriveObj": {
        "0": {
          "1": 510600001,
          "2": 510600021,
          "3": 510600022,
          "4": 510600023,
          "5": 510600024,
          "6": 510600025,
          "7": 510600026,
          "8": 510600028,
          "9": 510600029,
          "10": 510600030,
          "11": 510600031,
          "12": 510600037,
          "13": 510600041,
          "14": 510600042,
          "15": 510600043,
          "16": 510600044,
          "17": 510600045,
          "18": 510600046,
          "19": 510600047,
          "20": 510600048,
          "21": 510600049,
          "22": 510600050,
          "23": 510600003,
          "24": 510600004,
          "25": 510600005,
          "26": 510600006,
          "27": 510600061,
          "28": 510600065,
          "29": 510600066,
          "30": 510600068,
          "31": 510600064,
          "32": 510600051,
          "33": 510600070,
          "34": 510600071,
          "35": 510600072,
          "36": 510600074,
          "37": 510600009,
          "38": 510600075,
          "39": 510600082,
          "40": 510600083,
          "41": 510600084,
          "42": 510600085,
          "43": 510600086,
          "44": 510600087,
          "45": 510600088,
          "46": 510600089,
          "47": 510600027,
          "48": 510600076,
          "49": 510600077,
          "50": 510600078
        },
        "510600009": {
          "1": 510600008
        }
      },
      "LaserGroup": {
        "0": {
          "1": 510600001,
          "2": 510600021,
          "3": 510600022,
          "4": 510600023,
          "5": 510600024,
          "6": 510600025,
          "7": 510600026,
          "8": 510600028,
          "9": 510600029,
          "10": 510600030,
          "11": 510600031,
          "12": 510600037,
          "13": 510600041,
          "14": 510600042,
          "15": 510600043,
          "16": 510600044,
          "17": 510600045,
          "18": 510600046,
          "19": 510600047,
          "20": 510600048,
          "21": 510600049,
          "22": 510600050,
          "23": 510600003,
          "24": 510600004,
          "25": 510600005,
          "26": 510600006,
          "27": 510600061,
          "28": 510600065,
          "29": 510600066,
          "30": 510600068,
          "31": 510600064,
          "32": 510600051,
          "33": 510600070,
          "34": 510600071,
          "35": 510600072,
          "36": 510600074,
          "37": 510600008,
          "38": 510600009,
          "39": 510600075,
          "40": 510600082,
          "41": 510600083,
          "42": 510600084,
          "43": 510600085,
          "44": 510600086,
          "45": 510600087,
          "46": 510600088,
          "47": 510600089,
          "48": 510600027,
          "49": 510600076,
          "50": 510600077,
          "51": 510600078
        }
      },
      "BpGroup": {
        "0": {
          "1": 510600001,
          "2": 510600021,
          "3": 510600022,
          "4": 510600023,
          "5": 510600024,
          "6": 510600025,
          "7": 510600026,
          "8": 510600028,
          "9": 510600029,
          "10": 510600030,
          "11": 510600031,
          "12": 510600037,
          "13": 510600041,
          "14": 510600042,
          "15": 510600043,
          "16": 510600044,
          "17": 510600045,
          "18": 510600046,
          "19": 510600047,
          "20": 510600048,
          "21": 510600049,
          "22": 510600050,
          "23": 510600061,
          "24": 510600065,
          "25": 510600066,
          "26": 510600068,
          "27": 510600064,
          "28": 510600051,
          "29": 510600070,
          "30": 510600071,
          "31": 510600072,
          "32": 510600074,
          "33": 510600008,
          "34": 510600009,
          "35": 510600075,
          "36": 510600082,
          "37": 510600083,
          "38": 510600084,
          "39": 510600085,
          "40": 510600086,
          "41": 510600087,
          "42": 510600088,
          "43": 510600089,
          "44": 510600027,
          "45": 510600076,
          "46": 510600077,
          "47": 510600078
        },
        "1001": {
          "1": 510600003,
          "2": 510600004,
          "3": 510600005,
          "4": 510600006
        }
      },
      "MovableRange": {
        "0": {
          "1": 510600001,
          "2": 510600021,
          "3": 510600022,
          "4": 510600023,
          "5": 510600024,
          "6": 510600025,
          "7": 510600026,
          "8": 510600028,
          "9": 510600029,
          "10": 510600030,
          "11": 510600031,
          "12": 510600037,
          "13": 510600041,
          "14": 510600042,
          "15": 510600043,
          "16": 510600044,
          "17": 510600045,
          "18": 510600046,
          "19": 510600047,
          "20": 510600048,
          "21": 510600049,
          "22": 510600050,
          "23": 510600003,
          "24": 510600004,
          "25": 510600005,
          "26": 510600006,
          "27": 510600061,
          "28": 510600065,
          "29": 510600066,
          "30": 510600068,
          "31": 510600064,
          "32": 510600051,
          "33": 510600070,
          "34": 510600071,
          "35": 510600072,
          "36": 510600074,
          "37": 510600008,
          "38": 510600009,
          "39": 510600075,
          "40": 510600082,
          "41": 510600083,
          "42": 510600084,
          "43": 510600085,
          "44": 510600086,
          "45": 510600087,
          "46": 510600088,
          "47": 510600089,
          "48": 510600027,
          "49": 510600076,
          "50": 510600077,
          "51": 510600078
        }
      },
      "MapRangeID": {
        "0": {
          "1": 510600001,
          "2": 510600021,
          "3": 510600022,
          "4": 510600023,
          "5": 510600024,
          "6": 510600025,
          "7": 510600026,
          "8": 510600028,
          "9": 510600029,
          "10": 510600030,
          "11": 510600031,
          "12": 510600037,
          "13": 510600041,
          "14": 510600042,
          "15": 510600043,
          "16": 510600044,
          "17": 510600045,
          "18": 510600046,
          "19": 510600047,
          "20": 510600048,
          "21": 510600049,
          "22": 510600050,
          "23": 510600003,
          "24": 510600004,
          "25": 510600005,
          "26": 510600006,
          "27": 510600061,
          "28": 510600065,
          "29": 510600066,
          "30": 510600068,
          "31": 510600064,
          "32": 510600051,
          "33": 510600070,
          "34": 510600071,
          "35": 510600072,
          "36": 510600074,
          "37": 510600008,
          "38": 510600009,
          "39": 510600075,
          "40": 510600082,
          "41": 510600083,
          "42": 510600084,
          "43": 510600085,
          "44": 510600086,
          "45": 510600087,
          "46": 510600088,
          "47": 510600089,
          "48": 510600027,
          "49": 510600076,
          "50": 510600077,
          "51": 510600078
        }
      },
      "MonsterBindObjectIDs": {},
      "IsExplUse": {
        "false": {
          "1": 510600001,
          "2": 510600021,
          "3": 510600022,
          "4": 510600023,
          "5": 510600024,
          "6": 510600025,
          "7": 510600026,
          "8": 510600028,
          "9": 510600029,
          "10": 510600030,
          "11": 510600031,
          "12": 510600037,
          "13": 510600041,
          "14": 510600042,
          "15": 510600043,
          "16": 510600044,
          "17": 510600045,
          "18": 510600046,
          "19": 510600047,
          "20": 510600048,
          "21": 510600049,
          "22": 510600050,
          "23": 510600003,
          "24": 510600004,
          "25": 510600005,
          "26": 510600006,
          "27": 510600061,
          "28": 510600065,
          "29": 510600066,
          "30": 510600068,
          "31": 510600064,
          "32": 510600051,
          "33": 510600070,
          "34": 510600071,
          "35": 510600072,
          "36": 510600074,
          "37": 510600008,
          "38": 510600009,
          "39": 510600075,
          "40": 510600082,
          "41": 510600083,
          "42": 510600084,
          "43": 510600085,
          "44": 510600086,
          "45": 510600087,
          "46": 510600088,
          "47": 510600089,
          "48": 510600027,
          "49": 510600076,
          "50": 510600077,
          "51": 510600078
        }
      },
      "ExtraRulesID": {
        "0": {
          "1": 510600001,
          "2": 510600021,
          "3": 510600022,
          "4": 510600023,
          "5": 510600024,
          "6": 510600025,
          "7": 510600026,
          "8": 510600028,
          "9": 510600029,
          "10": 510600030,
          "11": 510600031,
          "12": 510600037,
          "13": 510600041,
          "14": 510600042,
          "15": 510600043,
          "16": 510600044,
          "17": 510600045,
          "18": 510600046,
          "19": 510600047,
          "20": 510600048,
          "21": 510600049,
          "22": 510600050,
          "23": 510600004,
          "24": 510600005,
          "25": 510600006,
          "26": 510600061,
          "27": 510600065,
          "28": 510600066,
          "29": 510600068,
          "30": 510600064,
          "31": 510600051,
          "32": 510600070,
          "33": 510600071,
          "34": 510600072,
          "35": 510600074,
          "36": 510600008,
          "37": 510600009,
          "38": 510600075,
          "39": 510600082,
          "40": 510600083,
          "41": 510600084,
          "42": 510600085,
          "43": 510600086,
          "44": 510600087,
          "45": 510600088,
          "46": 510600089,
          "47": 510600027,
          "48": 510600076,
          "49": 510600077,
          "50": 510600078
        },
        "2023": {
          "1": 510600003
        }
      },
      "SeasonType": {
        "106": {
          "1": 510600001,
          "2": 510600021,
          "3": 510600022,
          "4": 510600023,
          "5": 510600024,
          "6": 510600025,
          "7": 510600026,
          "8": 510600028,
          "9": 510600029,
          "10": 510600030,
          "11": 510600031,
          "12": 510600037,
          "13": 510600041,
          "14": 510600042,
          "15": 510600043,
          "16": 510600044,
          "17": 510600045,
          "18": 510600046,
          "19": 510600047,
          "20": 510600048,
          "21": 510600049,
          "22": 510600050,
          "23": 510600003,
          "24": 510600004,
          "25": 510600005,
          "26": 510600006,
          "27": 510600061,
          "28": 510600065,
          "29": 510600066,
          "30": 510600068,
          "31": 510600064,
          "32": 510600051,
          "33": 510600070,
          "34": 510600071,
          "35": 510600072,
          "36": 510600074,
          "37": 510600008,
          "38": 510600009,
          "39": 510600075,
          "40": 510600082,
          "41": 510600083,
          "42": 510600084,
          "43": 510600085,
          "44": 510600086,
          "45": 510600087,
          "46": 510600088,
          "47": 510600089,
          "48": 510600027,
          "49": 510600076,
          "50": 510600077,
          "51": 510600078
        }
      },
      "RetroExploration": {
        "0": {
          "1": 510600001,
          "2": 510600021,
          "3": 510600022,
          "4": 510600023,
          "5": 510600024,
          "6": 510600025,
          "7": 510600026,
          "8": 510600028,
          "9": 510600029,
          "10": 510600030,
          "11": 510600031,
          "12": 510600037,
          "13": 510600041,
          "14": 510600042,
          "15": 510600043,
          "16": 510600044,
          "17": 510600045,
          "18": 510600046,
          "19": 510600047,
          "20": 510600048,
          "21": 510600049,
          "22": 510600050,
          "23": 510600003,
          "24": 510600004,
          "25": 510600005,
          "26": 510600006,
          "27": 510600061,
          "28": 510600065,
          "29": 510600066,
          "30": 510600068,
          "31": 510600064,
          "32": 510600051,
          "33": 510600070,
          "34": 510600071,
          "35": 510600072,
          "36": 510600074,
          "37": 510600008,
          "38": 510600009,
          "39": 510600075,
          "40": 510600082,
          "41": 510600083,
          "42": 510600084,
          "43": 510600085,
          "44": 510600086,
          "45": 510600087,
          "46": 510600088,
          "47": 510600089,
          "48": 510600027,
          "49": 510600076,
          "50": 510600077,
          "51": 510600078
        }
      },
      "HSInsID": {
        "0": {
          "1": 510600001,
          "2": 510600021,
          "3": 510600022,
          "4": 510600023,
          "5": 510600024,
          "6": 510600025,
          "7": 510600026,
          "8": 510600028,
          "9": 510600029,
          "10": 510600030,
          "11": 510600031,
          "12": 510600037,
          "13": 510600041,
          "14": 510600042,
          "15": 510600043,
          "16": 510600044,
          "17": 510600045,
          "18": 510600046,
          "19": 510600047,
          "20": 510600048,
          "21": 510600049,
          "22": 510600050,
          "23": 510600003,
          "24": 510600004,
          "25": 510600005,
          "26": 510600006,
          "27": 510600061,
          "28": 510600065,
          "29": 510600066,
          "30": 510600068,
          "31": 510600064,
          "32": 510600051,
          "33": 510600070,
          "34": 510600071,
          "35": 510600072,
          "36": 510600074,
          "37": 510600008,
          "38": 510600009,
          "39": 510600075,
          "40": 510600082,
          "41": 510600083,
          "42": 510600084,
          "43": 510600085,
          "44": 510600086,
          "45": 510600087,
          "46": 510600088,
          "47": 510600089,
          "48": 510600027,
          "49": 510600076,
          "50": 510600077,
          "51": 510600078
        }
      }
    }
  }
}
