{
  "_meta": {
    "table": "BattleMonsterWave",
    "source_table": "BattleMonsterWave",
    "format": "mapping_table",
    "entry_count": 1
  },
  "data": {
    "Split": {
      "BattleMonsterWave_Main_2IndexTable": {
        "Hardness": {
          "0": {
            "1": 3100,
            "2": 3101,
            "3": 3102,
            "4": 3103,
            "5": 3110,
            "6": 3111,
            "7": 3120,
            "8": 3121,
            "9": 3130,
            "10": 3140,
            "11": 3141,
            "12": 3150,
            "13": 3151,
            "14": 3160,
            "15": 3161,
            "16": 30082,
            "17": 30083,
            "18": 30084,
            "19": 30085,
            "20": 30092,
            "21": 3098,
            "22": 3099,
            "23": 3109,
            "24": 3119,
            "25": 3129,
            "26": 30401102,
            "27": 30401103,
            "28": 30403302,
            "29": 30403303,
            "30": 10170102,
            "31": 10170202,
            "32": 10170203
          }
        }
      }
    }
  }
}
