{
  "_meta": {
    "table": "VehicleType",
    "header_table": "VehicleTypeHeaderTable",
    "format": "flat_rows",
    "schema_size": 23,
    "row_count": 10,
    "array_fields": [
      "CameraFollowOffset",
      "LocoState",
      "PlayerTrigger"
    ],
    "unresolved_array_refs": 30
  },
  "default": {
    "ID": "null",
    "FCName": null,
    "LocoState": {},
    "PlayerTrigger": {},
    "OverrideAnimatorPostFix": null,
    "VehicleDefaultRate": 0,
    "CameraFollowOffset": {},
    "VehicleCameraFOV": 0,
    "VehicleUnlockFogRange": 0,
    "VehicleMoveSpeed": 0,
    "VehicleHeightOffset": 0,
    "VehicleTurningSpeed": 0,
    "VehicleTurningAngle": 0,
    "VehicleSmallMapCameraHeight": 0,
    "VehicleFarFreeCamaraZoomRate": 0,
    "AlignWithJoystickDirection": false,
    "VehicleLocoAcceleration": 0,
    "VehicleLocoAccelerationRate": 0,
    "VehicleLocoDecelration": 0,
    "VehicleLocoDecelrationRate": 0,
    "SailOutwardTurnSpeed": 0,
    "SailInwardTurnSpeed": 0,
    "ShowProtagonistModel": false
  },
  "row_keys": [
    "LakeShip",
    "Ship",
    "Skate",
    "LavaShip",
    "Wolf",
    "Hamster",
    "Snowman",
    "Sheep",
    "Role",
    "NormalPlayer"
  ],
  "rows": [
    {
      "ID": "LakeShip",
      "FCName": null,
      "LocoState": {
        "$arrayRef": 77303
      },
      "PlayerTrigger": {
        "$arrayRef": 99914
      },
      "OverrideAnimatorPostFix": "ship",
      "VehicleDefaultRate": 0.45,
      "CameraFollowOffset": {
        "$arrayRef": 99915
      },
      "VehicleCameraFOV": 21.5,
      "VehicleUnlockFogRange": 7,
      "VehicleMoveSpeed": 1.3,
      "VehicleHeightOffset": 0.2,
      "VehicleTurningSpeed": 115,
      "VehicleTurningAngle": 1,
      "VehicleSmallMapCameraHeight": 85,
      "VehicleFarFreeCamaraZoomRate": 0.55,
      "AlignWithJoystickDirection": false,
      "VehicleLocoAcceleration": 0.005,
      "VehicleLocoAccelerationRate": 0,
      "VehicleLocoDecelration": 0.002,
      "VehicleLocoDecelrationRate": 0.005,
      "SailOutwardTurnSpeed": 2,
      "SailInwardTurnSpeed": 0.5,
      "ShowProtagonistModel": true
    },
    {
      "ID": "Ship",
      "FCName": null,
      "LocoState": {
        "$arrayRef": 77303
      },
      "PlayerTrigger": {
        "$arrayRef": 99914
      },
      "OverrideAnimatorPostFix": "ship",
      "VehicleDefaultRate": 0.45,
      "CameraFollowOffset": {
        "$arrayRef": 99915
      },
      "VehicleCameraFOV": 21.5,
      "VehicleUnlockFogRange": 7,
      "VehicleMoveSpeed": 1.6,
      "VehicleHeightOffset": 0.5,
      "VehicleTurningSpeed": 115,
      "VehicleTurningAngle": 1,
      "VehicleSmallMapCameraHeight": 85,
      "VehicleFarFreeCamaraZoomRate": 0.55,
      "AlignWithJoystickDirection": false,
      "VehicleLocoAcceleration": 0.005,
      "VehicleLocoAccelerationRate": 0,
      "VehicleLocoDecelration": 0.002,
      "VehicleLocoDecelrationRate": 0.005,
      "SailOutwardTurnSpeed": 2,
      "SailInwardTurnSpeed": 0.5,
      "ShowProtagonistModel": true
    },
    {
      "ID": "Skate",
      "FCName": "PlayerSkate",
      "LocoState": {
        "$arrayRef": 77303
      },
      "PlayerTrigger": {
        "$arrayRef": 99914
      },
      "OverrideAnimatorPostFix": "skate",
      "VehicleDefaultRate": 0.45,
      "CameraFollowOffset": {
        "$arrayRef": 99915
      },
      "VehicleCameraFOV": 21.5,
      "VehicleUnlockFogRange": 7,
      "VehicleMoveSpeed": 1.8,
      "VehicleHeightOffset": 0.5,
      "VehicleTurningSpeed": 115,
      "VehicleTurningAngle": 1,
      "VehicleSmallMapCameraHeight": 85,
      "VehicleFarFreeCamaraZoomRate": 0.55,
      "AlignWithJoystickDirection": false,
      "VehicleLocoAcceleration": 0.005,
      "VehicleLocoAccelerationRate": 0.001,
      "VehicleLocoDecelration": 0,
      "VehicleLocoDecelrationRate": 0,
      "SailOutwardTurnSpeed": 2,
      "SailInwardTurnSpeed": 0.5,
      "ShowProtagonistModel": true
    },
    {
      "ID": "LavaShip",
      "FCName": "VehicleLava",
      "LocoState": {
        "$arrayRef": 77303
      },
      "PlayerTrigger": {
        "$arrayRef": 99914
      },
      "OverrideAnimatorPostFix": "ship",
      "VehicleDefaultRate": 0.45,
      "CameraFollowOffset": {
        "$arrayRef": 99915
      },
      "VehicleCameraFOV": 21.5,
      "VehicleUnlockFogRange": 7,
      "VehicleMoveSpeed": 1.3,
      "VehicleHeightOffset": 0.2,
      "VehicleTurningSpeed": 115,
      "VehicleTurningAngle": 1,
      "VehicleSmallMapCameraHeight": 85,
      "VehicleFarFreeCamaraZoomRate": 0.55,
      "AlignWithJoystickDirection": false,
      "VehicleLocoAcceleration": 0.005,
      "VehicleLocoAccelerationRate": 0,
      "VehicleLocoDecelration": 0.002,
      "VehicleLocoDecelrationRate": 0.005,
      "SailOutwardTurnSpeed": 2,
      "SailInwardTurnSpeed": 0.5,
      "ShowProtagonistModel": true
    },
    {
      "ID": "Wolf",
      "FCName": null,
      "LocoState": {
        "$arrayRef": 77303
      },
      "PlayerTrigger": {
        "$arrayRef": 99914
      },
      "OverrideAnimatorPostFix": "transform",
      "VehicleDefaultRate": 0.45,
      "CameraFollowOffset": {
        "$arrayRef": 99915
      },
      "VehicleCameraFOV": 15,
      "VehicleUnlockFogRange": 3,
      "VehicleMoveSpeed": 1,
      "VehicleHeightOffset": 0.2,
      "VehicleTurningSpeed": 1500,
      "VehicleTurningAngle": 10,
      "VehicleSmallMapCameraHeight": 85,
      "VehicleFarFreeCamaraZoomRate": 0.55,
      "AlignWithJoystickDirection": false,
      "VehicleLocoAcceleration": 1,
      "VehicleLocoAccelerationRate": 0,
      "VehicleLocoDecelration": 1,
      "VehicleLocoDecelrationRate": 0,
      "SailOutwardTurnSpeed": 0,
      "SailInwardTurnSpeed": 0,
      "ShowProtagonistModel": false
    },
    {
      "ID": "Hamster",
      "FCName": null,
      "LocoState": {
        "$arrayRef": 77303
      },
      "PlayerTrigger": {
        "$arrayRef": 99914
      },
      "OverrideAnimatorPostFix": "transform",
      "VehicleDefaultRate": 0.45,
      "CameraFollowOffset": {
        "$arrayRef": 99915
      },
      "VehicleCameraFOV": 15,
      "VehicleUnlockFogRange": 3,
      "VehicleMoveSpeed": 1,
      "VehicleHeightOffset": 0.2,
      "VehicleTurningSpeed": 1500,
      "VehicleTurningAngle": 10,
      "VehicleSmallMapCameraHeight": 85,
      "VehicleFarFreeCamaraZoomRate": 0.55,
      "AlignWithJoystickDirection": false,
      "VehicleLocoAcceleration": 1,
      "VehicleLocoAccelerationRate": 0,
      "VehicleLocoDecelration": 1,
      "VehicleLocoDecelrationRate": 0,
      "SailOutwardTurnSpeed": 0,
      "SailInwardTurnSpeed": 0,
      "ShowProtagonistModel": false
    },
    {
      "ID": "Snowman",
      "FCName": null,
      "LocoState": {
        "$arrayRef": 77303
      },
      "PlayerTrigger": {
        "$arrayRef": 99914
      },
      "OverrideAnimatorPostFix": "transform",
      "VehicleDefaultRate": 0.45,
      "CameraFollowOffset": {
        "$arrayRef": 99915
      },
      "VehicleCameraFOV": 15,
      "VehicleUnlockFogRange": 3,
      "VehicleMoveSpeed": 1,
      "VehicleHeightOffset": 0.2,
      "VehicleTurningSpeed": 1500,
      "VehicleTurningAngle": 10,
      "VehicleSmallMapCameraHeight": 85,
      "VehicleFarFreeCamaraZoomRate": 0.55,
      "AlignWithJoystickDirection": false,
      "VehicleLocoAcceleration": 1,
      "VehicleLocoAccelerationRate": 0,
      "VehicleLocoDecelration": 1,
      "VehicleLocoDecelrationRate": 0,
      "SailOutwardTurnSpeed": 0,
      "SailInwardTurnSpeed": 0,
      "ShowProtagonistModel": false
    },
    {
      "ID": "Sheep",
      "FCName": null,
      "LocoState": {
        "$arrayRef": 77303
      },
      "PlayerTrigger": {
        "$arrayRef": 99914
      },
      "OverrideAnimatorPostFix": "transform",
      "VehicleDefaultRate": 0.45,
      "CameraFollowOffset": {
        "$arrayRef": 99915
      },
      "VehicleCameraFOV": 15,
      "VehicleUnlockFogRange": 3,
      "VehicleMoveSpeed": 1,
      "VehicleHeightOffset": 0.2,
      "VehicleTurningSpeed": 1500,
      "VehicleTurningAngle": 10,
      "VehicleSmallMapCameraHeight": 85,
      "VehicleFarFreeCamaraZoomRate": 0.55,
      "AlignWithJoystickDirection": false,
      "VehicleLocoAcceleration": 1,
      "VehicleLocoAccelerationRate": 0,
      "VehicleLocoDecelration": 1,
      "VehicleLocoDecelrationRate": 0,
      "SailOutwardTurnSpeed": 0,
      "SailInwardTurnSpeed": 0,
      "ShowProtagonistModel": false
    },
    {
      "ID": "Role",
      "FCName": null,
      "LocoState": {
        "$arrayRef": 77303
      },
      "PlayerTrigger": {
        "$arrayRef": 99914
      },
      "OverrideAnimatorPostFix": "transform",
      "VehicleDefaultRate": 0.45,
      "CameraFollowOffset": {
        "$arrayRef": 99915
      },
      "VehicleCameraFOV": 15,
      "VehicleUnlockFogRange": 3,
      "VehicleMoveSpeed": 1,
      "VehicleHeightOffset": 0.2,
      "VehicleTurningSpeed": 1500,
      "VehicleTurningAngle": 10,
      "VehicleSmallMapCameraHeight": 85,
      "VehicleFarFreeCamaraZoomRate": 0.55,
      "AlignWithJoystickDirection": false,
      "VehicleLocoAcceleration": 1,
      "VehicleLocoAccelerationRate": 0,
      "VehicleLocoDecelration": 1,
      "VehicleLocoDecelrationRate": 0,
      "SailOutwardTurnSpeed": 0,
      "SailInwardTurnSpeed": 0,
      "ShowProtagonistModel": false
    },
    {
      "ID": "NormalPlayer",
      "FCName": null,
      "LocoState": {
        "$arrayRef": 77303
      },
      "PlayerTrigger": {
        "$arrayRef": 99914
      },
      "OverrideAnimatorPostFix": "transform",
      "VehicleDefaultRate": 0.45,
      "CameraFollowOffset": {
        "$arrayRef": 99915
      },
      "VehicleCameraFOV": 15,
      "VehicleUnlockFogRange": 3,
      "VehicleMoveSpeed": 1,
      "VehicleHeightOffset": 0.2,
      "VehicleTurningSpeed": 1500,
      "VehicleTurningAngle": 10,
      "VehicleSmallMapCameraHeight": 85,
      "VehicleFarFreeCamaraZoomRate": 0.55,
      "AlignWithJoystickDirection": false,
      "VehicleLocoAcceleration": 1,
      "VehicleLocoAccelerationRate": 0,
      "VehicleLocoDecelration": 1,
      "VehicleLocoDecelrationRate": 0,
      "SailOutwardTurnSpeed": 0,
      "SailInwardTurnSpeed": 0,
      "ShowProtagonistModel": true
    }
  ]
}
